odoo/addons/account_subsequence_fiscal_year/README.rst
odoo/addons/account_subsequence_fiscal_year/__init__.py
odoo/addons/account_subsequence_fiscal_year/__manifest__.py
odoo/addons/account_subsequence_fiscal_year/demo/res_groups.xml
odoo/addons/account_subsequence_fiscal_year/i18n/account_subsequence_fiscal_year.pot
odoo/addons/account_subsequence_fiscal_year/i18n/fr.po
odoo/addons/account_subsequence_fiscal_year/models/__init__.py
odoo/addons/account_subsequence_fiscal_year/models/account_bank_statement.py
odoo/addons/account_subsequence_fiscal_year/models/account_move.py
odoo/addons/account_subsequence_fiscal_year/models/ir_sequence.py
odoo/addons/account_subsequence_fiscal_year/models/res_company.py
odoo/addons/account_subsequence_fiscal_year/models/res_config_settings.py
odoo/addons/account_subsequence_fiscal_year/readme/CONFIGURE.rst
odoo/addons/account_subsequence_fiscal_year/readme/CONTRIBUTORS.rst
odoo/addons/account_subsequence_fiscal_year/readme/DESCRIPTION.rst
odoo/addons/account_subsequence_fiscal_year/static/description/icon.png
odoo/addons/account_subsequence_fiscal_year/static/description/index.html
odoo/addons/account_subsequence_fiscal_year/static/description/res_config_setting.png
odoo/addons/account_subsequence_fiscal_year/tests/__init__.py
odoo/addons/account_subsequence_fiscal_year/tests/test_module.py
odoo/addons/account_subsequence_fiscal_year/views/view_res_config_settings.xml
odoo12_addon_account_subsequence_fiscal_year-12.0.1.0.0.99.dev5.dist-info/METADATA
odoo12_addon_account_subsequence_fiscal_year-12.0.1.0.0.99.dev5.dist-info/WHEEL
odoo12_addon_account_subsequence_fiscal_year-12.0.1.0.0.99.dev5.dist-info/top_level.txt
odoo12_addon_account_subsequence_fiscal_year-12.0.1.0.0.99.dev5.dist-info/RECORD
